mcp_linkedin/__init__.py
mcp_linkedin/client.py
mseep_mcp_linkedin-0.1.5.dist-info/licenses/LICENSE
mseep_mcp_linkedin-0.1.5.dist-info/METADATA
mseep_mcp_linkedin-0.1.5.dist-info/WHEEL
mseep_mcp_linkedin-0.1.5.dist-info/entry_points.txt
mseep_mcp_linkedin-0.1.5.dist-info/top_level.txt
mseep_mcp_linkedin-0.1.5.dist-info/RECORD
